{
    "events": [
        {
            "title": "dababy",
            "description": "dababy",
            "datum": "dababy",
            "werk": "mantelzorg"
        },
        {
            "title": "dababy",
            "description": "dababy",
            "datum": "dababy",
            "werk": "mantelzorg"
        },
        {
            "title": "dababy",
            "description": "dababy",
            "datum": "dababy",
            "werk": "mantelzorg"
        },
        {
            "title": "dababy",
            "description": "dababy",
            "datum": "dababy",
            "werk": "mantelzorg"
        },
        {
            "title": "dababy",
            "description": "dababy",
            "datum": "dababy",
            "werk": "mantelzorg"
        },
        {
            "title": "dababy",
            "description": "dababy",
            "datum": "dababy",
            "werk": "mantelzorg"
        }
    ]
}